{
    "home":"হোম",
    "about": "আমাদের সম্পর্কে",
    "shop": "শপ",
    "contact": "আমাদের সাথে যোগাযোগ",
    "login": "লগইন",
    "register": "রেজিস্টার করুন",
    "logout": "লগআউট",
    "cart": "কার্ট",
    "search": "অনুসন্ধান",
    "wishlist": "ইচ্ছেতালিকা",
    "account": "অ্যাকাউন্ট",
    "addtocart": "কার্টে যুক্ত করুন",
    "top_new_arrival": "নতুন আগমন",
    "trending_products": "ট্রেন্ডিং পণ্য",
    "shopbycategory": "বিভাগ অনুসারে কেনাকাটা করুন",
    "free_shipping": "ফ্রি শিপিং",
    "money_return": "টাকা ফেরত",
    "support_24_7": "24/7 সহায়তা",
    "categories": "ক্যাটাগরি",
    "allCategories": "সব ধরনের",
    "price": "মূল্য",
    "size": "সাইজ",
    "color": "রং",
    "brand": "ব্রান্ড",
    "rating": "রেটিং",
    "filter": "ফিল্টার",
    "clear": "পরিষ্কার",
    "sort": "সাজানো",
    "product": "পণ্য",
    "products": "পণ্য",
    "product_details": "পণ্যের বিবরণ",
    "description": "বিবরণ",
    "reviews": "রিভিউ",
    "related_products": "সম্পর্কিত পণ্য",
    "checkout": "চেক আউট",
    "order_summary": "অর্ডার সারসংক্ষেপ",
    "shipping" : "শিপিং",
    "payment": "পেমেন্ট",
    "total": "মোট",
    "place_order": "অর্ডার করুন",
    "fName": "নামের প্রথম অংশ",
    "lName": "নামের শেষাংশ",
    "email": "ইমেইল",
    "phone": "ফোন",
    "country_region": "দেশ/অঞ্চল",
    "street_address": "রাস্তার ঠিকানা",
    "city": "শহর",
    "company": "কোম্পানি",
    "forgot_password": "পাসওয়ার্ড ভুলে গেছেন",
    "remember_me": "আমাকে মনে রেখো",
    "password": "পাসওয়ার্ড",
    "confirm_password": "পাসওয়ার্ড নিশ্চিত করুন",
    "full_name": "সম্পূর্ণ নাম",
    "email_address": "ইমেইল ঠিকানা",
    "phone_number": "ফোন নাম্বার",
    "create_account": "অ্যাকাউন্ট তৈরি করুন"
}